cz_bitbucket_jira_conventional.py
cz_bitbucket_jira_conventional-1.1.1.dist-info/LICENSE
cz_bitbucket_jira_conventional-1.1.1.dist-info/METADATA
cz_bitbucket_jira_conventional-1.1.1.dist-info/WHEEL
cz_bitbucket_jira_conventional-1.1.1.dist-info/top_level.txt
cz_bitbucket_jira_conventional-1.1.1.dist-info/RECORD
