Metadata-Version: 2.1
Name: cz-bitbucket-jira-conventional
Version: 1.1.1
Summary: Extend the commitizen tools to create conventional commits and README that link to Jira and Bitbucket.
Home-page: https://github.com/xayon/cz-bitbucket-jira-conventional
Author: Falko Krause, apheris AI GmbH
Author-email: f.krause@apheris.com
License: MIT
Platform: UNKNOWN
License-File: LICENSE
Requires-Dist: commitizen
